autodocipy/__init__.py
autodocipy/autodoc.py
autodocipy/thirdparty.py
mypackage/__init__.py
mypackage/autodoc.py
mypackage/thirdparty.py
autodocipy-1.0.dist-info/METADATA
autodocipy-1.0.dist-info/WHEEL
autodocipy-1.0.dist-info/entry_points.txt
autodocipy-1.0.dist-info/top_level.txt
autodocipy-1.0.dist-info/RECORD
