Metadata-Version: 2.1
Name: autodocipy
Version: 1.0
Requires-Dist: openai
